{
	"metadata": {
		"version": 4.4,
		"type": "BufferGeometry",
		"generator": "pythonOCC"
	},
	"uuid": "fddb446f194c43ccb4f1832c5a1f89ac",
	"type": "BufferGeometry",
	"data": {
	"attributes": {
			"position": {
				"itemSize": 3,
				"type": "Float32Array",
				"array": [23.4578,-16.7528,-3.14953,23.4438,-16.7528,-3.14953,23.4438,-16.7848,-3.11913,23.4578,-16.7528,-3.14953,23.4438,-16.7848,-3.11913,23.4578,-16.7848,-3.11913]
			},
			"normal": {
				"itemSize": 3,
				"type": "Float32Array",
				"array": [0,0.688749,0.724999,0,0.688749,0.724999,0,0.688749,0.724999,0,0.688749,0.724999,0,0.688749,0.724999,0,0.688749,0.724999]
			}
		}
	}
}
